jinja2loader.py
setup.py
Jinja2Loader.egg-info/PKG-INFO
Jinja2Loader.egg-info/SOURCES.txt
Jinja2Loader.egg-info/dependency_links.txt
Jinja2Loader.egg-info/not-zip-safe
Jinja2Loader.egg-info/requires.txt
Jinja2Loader.egg-info/top_level.txt